{
"2":"CT_INT",
"11":"OPR_PM",
"39":"OPR_SUM",
"46":"FN_DCLR",
"25":"O_BRCKT",
"42":"PARAMS",
"29":"O_PRTSIS",
"8":"ID",
"20":"BLK_IF",
"14":"OPRLR_EQ",
"31":"OPR_ATR",
"33":"IDT_FLOAT",
"18":"FN_READ",
"26":"C_BRCKT",
"35":"IDT_STRING",
"17":"FN_PRINT",
"49":"OPR_CONCAT",
"44":"EXP_BOOL",
"4":"CT_FLOAT",
"37":"VEC_IN",
"45":"VOID",
"13":"OPRLN",
"30":"C_PRTSIS",
"1":"CT_VALUE",
"47":"FN_CALL",
"32":"IDT_INT",
"50":"OPR_UN_NEG",
"40":"OPR_SUB",
"7":"EPS",
"9":"CONST",
"43":"IDT_BOOL",
"34":"IDT_CHAR",
"3":"CT_CHAR",
"38":"LEX_ERR",
"48":"CT_STRING",
"36":"FN_MAIN",
"12":"OPR_DM",
"-1":"EOF",
"16":"OPRLR_LGEQ",
"21":"BLK_ELS",
"10":"EXPR",
"19":"DREAD",
"22":"BLK_FOR",
"6":"SMCL",
"24":"COMMA",
"28":"C_C_BRCKT",
"5":"CT_VEC",
"23":"BLK_WHILE",
"27":"O_C_BRCKT",
"15":"OPRLR_LG",
"41":"CTN",
"51":"OPRLR_GT",
"52":"RETURN",
"53":"OPRLR_GEQ",
"54":"OPRLR_LGEQ",
"55":"OPR_CONCAT"
}

